{
    "last_update": "2020-07-13T00:02:07",
    "members": [
        {
            "username": "@jkt48.ume",
            "follower": 6858,
            "following": 127,
            "posts": 12
        },
        {
            "username": "@jkt48nabila_",
            "follower": 4112,
            "following": 84,
            "posts": 10
        },
        {
            "username": "@jkt48.bri",
            "follower": 9544,
            "following": 139,
            "posts": 13
        },
        {
            "username": "@jkt48.febi",
            "follower": 15447,
            "following": 461,
            "posts": 7
        },
        {
            "username": "@jkt48.alma",
            "follower": 10474,
            "following": 61,
            "posts": 11
        },
        {
            "username": "@jkt48.lisa",
            "follower": 39296,
            "following": 389,
            "posts": 56
        },
        {
            "username": "@jkt48zahra_",
            "follower": 6282,
            "following": 138,
            "posts": 18
        },
        {
            "username": "@jkt48.marsha",
            "follower": 10147,
            "following": 182,
            "posts": 7
        },
        {
            "username": "@jkt48.shinta",
            "follower": 6229,
            "following": 117,
            "posts": 12
        },
        {
            "username": "@jkt48.keisya",
            "follower": 7404,
            "following": 118,
            "posts": 9
        },
        {
            "username": "@jkt48.vany",
            "follower": 10455,
            "following": 163,
            "posts": 28
        },
        {
            "username": "@jkt48.kathrina",
            "follower": 7168,
            "following": 217,
            "posts": 10
        },
        {
            "username": "@jkt48.ashel",
            "follower": 11166,
            "following": 148,
            "posts": 12
        },
        {
            "username": "@jkt48.adel",
            "follower": 12434,
            "following": 181,
            "posts": 34
        },
        {
            "username": "@jkt48.flora",
            "follower": 10687,
            "following": 126,
            "posts": 13
        },
        {
            "username": "@jkt48.lulu",
            "follower": 9289,
            "following": 238,
            "posts": 23
        },
        {
            "username": "@jkt48tasya",
            "follower": 22098,
            "following": 213,
            "posts": 48
        },
        {
            "username": "@jkt48.nunu",
            "follower": 15173,
            "following": 179,
            "posts": 39
        },
        {
            "username": "@jkt48indy",
            "follower": 24299,
            "following": 360,
            "posts": 65
        },
        {
            "username": "@jkt48.aiko",
            "follower": 14109,
            "following": 184,
            "posts": 22
        },
        {
            "username": "@jkt48.olla",
            "follower": 14390,
            "following": 160,
            "posts": 34
        },
        {
            "username": "@jkt48indah_",
            "follower": 11918,
            "following": 100,
            "posts": 18
        },
        {
            "username": "@jkt48shalzag",
            "follower": 22240,
            "following": 186,
            "posts": 14
        },
        {
            "username": "@jkt48.caithlyn",
            "follower": 8086,
            "following": 159,
            "posts": 27
        },
        {
            "username": "@jkt48.chalista",
            "follower": 12097,
            "following": 97,
            "posts": 37
        },
        {
            "username": "@jkt48nanda",
            "follower": 30524,
            "following": 199,
            "posts": 30
        },
        {
            "username": "@jkt48.jessi",
            "follower": 18530,
            "following": 299,
            "posts": 54
        },
        {
            "username": "@jkt48.chika",
            "follower": 31381,
            "following": 153,
            "posts": 33
        },
        {
            "username": "@jkt48gita",
            "follower": 20741,
            "following": 127,
            "posts": 46
        },
        {
            "username": "@jkt48.diani",
            "follower": 63721,
            "following": 264,
            "posts": 111
        },
        {
            "username": "@jkt48.jesslyn",
            "follower": 17543,
            "following": 227,
            "posts": 37
        },
        {
            "username": "@jkt48.abel",
            "follower": 8943,
            "following": 173,
            "posts": 33
        },
        {
            "username": "@jkt48.oniel",
            "follower": 16218,
            "following": 155,
            "posts": 25
        },
        {
            "username": "@jkt48.julie",
            "follower": 71159,
            "following": 349,
            "posts": 110
        },
        {
            "username": "@jkt48nadila",
            "follower": 100766,
            "following": 304,
            "posts": 46
        },
        {
            "username": "@jkt48aurel",
            "follower": 85160,
            "following": 406,
            "posts": 109
        },
        {
            "username": "@jkt48.eli",
            "follower": 27811,
            "following": 359,
            "posts": 73
        },
        {
            "username": "@jkt48.freya",
            "follower": 26475,
            "following": 414,
            "posts": 46
        },
        {
            "username": "@jkt48.christy",
            "follower": 37705,
            "following": 184,
            "posts": 35
        },
        {
            "username": "@jkt48.ratu",
            "follower": 23745,
            "following": 183,
            "posts": 13
        },
        {
            "username": "@jkt48aby",
            "follower": 58152,
            "following": 519,
            "posts": 99
        },
        {
            "username": "@jkt48feni",
            "follower": 102104,
            "following": 222,
            "posts": 105
        },
        {
            "username": "@jkt48ramel",
            "follower": 44066,
            "following": 195,
            "posts": 59
        },
        {
            "username": "@jkt48melati",
            "follower": 91639,
            "following": 477,
            "posts": 153
        },
        {
            "username": "@jkt48.celine",
            "follower": 57421,
            "following": 324,
            "posts": 72
        },
        {
            "username": "@jkt48jinan",
            "follower": 96213,
            "following": 240,
            "posts": 188
        },
        {
            "username": "@jkt48.ara",
            "follower": 22597,
            "following": 149,
            "posts": 24
        },
        {
            "username": "@jkt48.yori",
            "follower": 42625,
            "following": 215,
            "posts": 43
        },
        {
            "username": "@jkt48.afiqaah",
            "follower": 33473,
            "following": 160,
            "posts": 38
        },
        {
            "username": "@jkt48.brielle",
            "follower": 38028,
            "following": 230,
            "posts": 40
        },
        {
            "username": "@jkt48ariel",
            "follower": 55372,
            "following": 414,
            "posts": 147
        },
        {
            "username": "@jkt48.mira",
            "follower": 28777,
            "following": 196,
            "posts": 38
        },
        {
            "username": "@jkt48rona",
            "follower": 135083,
            "following": 566,
            "posts": 675
        },
        {
            "username": "@jkt48.dey",
            "follower": 34395,
            "following": 153,
            "posts": 79
        },
        {
            "username": "@jkt48.vivi",
            "follower": 26470,
            "following": 234,
            "posts": 26
        },
        {
            "username": "@jkt48.fiony",
            "follower": 28264,
            "following": 236,
            "posts": 38
        },
        {
            "username": "@jkt48.lala",
            "follower": 50672,
            "following": 234,
            "posts": 47
        },
        {
            "username": "@jkt48.eve",
            "follower": 128525,
            "following": 357,
            "posts": 60
        },
        {
            "username": "@jkt48.zee",
            "follower": 83074,
            "following": 149,
            "posts": 34
        },
        {
            "username": "@jkt48fia",
            "follower": 95264,
            "following": 286,
            "posts": 195
        },
        {
            "username": "@jkt48gaby",
            "follower": 165874,
            "following": 610,
            "posts": 167
        },
        {
            "username": "@jkt48beby",
            "follower": 63593,
            "following": 231,
            "posts": 307
        },
        {
            "username": "@jkt48cinhap",
            "follower": 95622,
            "following": 284,
            "posts": 52
        },
        {
            "username": "@jkt48.muthe_",
            "follower": 41338,
            "following": 167,
            "posts": 64
        },
        {
            "username": "@jkt48.aya",
            "follower": 89817,
            "following": 269,
            "posts": 59
        },
        {
            "username": "@jkt48frieska",
            "follower": 157844,
            "following": 543,
            "posts": 559
        },
        {
            "username": "@jkt48anin",
            "follower": 169857,
            "following": 368,
            "posts": 44
        },
        {
            "username": "@jkt48sisca",
            "follower": 179834,
            "following": 635,
            "posts": 561
        },
        {
            "username": "@jkt48gracia",
            "follower": 220252,
            "following": 590,
            "posts": 324
        },
        {
            "username": "@jkt48shani",
            "follower": 247271,
            "following": 430,
            "posts": 276
        },
        {
            "username": "@jkt48desy",
            "follower": 308946,
            "following": 849,
            "posts": 745
        }
    ]
}