{
    "last_update": "2020-05-26T00:00:02",
    "members": [
        {
            "username": "@GNabilaJKT48",
            "follower": 6398,
            "following": 123,
            "likes": 221,
            "tweets": 241
        },
        {
            "username": "@P_ZahraJKT48",
            "follower": 8044,
            "following": 105,
            "likes": 3279,
            "tweets": 393
        },
        {
            "username": "@D_ShintaJKT48",
            "follower": 9060,
            "following": 98,
            "likes": 491,
            "tweets": 338
        },
        {
            "username": "@L_MarshaJKT48",
            "follower": 12932,
            "following": 168,
            "likes": 896,
            "tweets": 247
        },
        {
            "username": "@I_KathrinaJKT48",
            "follower": 8136,
            "following": 153,
            "likes": 274,
            "tweets": 201
        },
        {
            "username": "@C_IndahJKT48",
            "follower": 9839,
            "following": 95,
            "likes": 22,
            "tweets": 321
        },
        {
            "username": "@E_ChalistaJKT48",
            "follower": 10750,
            "following": 93,
            "likes": 977,
            "tweets": 310
        },
        {
            "username": "@G_CaithlynJKT48",
            "follower": 8084,
            "following": 118,
            "likes": 914,
            "tweets": 357
        },
        {
            "username": "@S_AshelJKT48",
            "follower": 15902,
            "following": 100,
            "likes": 461,
            "tweets": 280
        },
        {
            "username": "@J_AbelJKT48",
            "follower": 7434,
            "following": 124,
            "likes": 657,
            "tweets": 160
        },
        {
            "username": "@N_RatuJKT48",
            "follower": 32202,
            "following": 123,
            "likes": 327,
            "tweets": 578
        },
        {
            "username": "@C_NunuJKT48",
            "follower": 31266,
            "following": 146,
            "likes": 1260,
            "tweets": 869
        },
        {
            "username": "@M_UmeJKT48",
            "follower": 18510,
            "following": 93,
            "likes": 142,
            "tweets": 923
        },
        {
            "username": "@S_FloraJKT48",
            "follower": 21461,
            "following": 102,
            "likes": 68,
            "tweets": 410
        },
        {
            "username": "@R_KeisyaJKT48",
            "follower": 26639,
            "following": 92,
            "likes": 425,
            "tweets": 760
        },
        {
            "username": "@F_MiraJKT48",
            "follower": 43997,
            "following": 105,
            "likes": 234,
            "tweets": 1670
        },
        {
            "username": "@A_FionyJKT48",
            "follower": 45558,
            "following": 160,
            "likes": 514,
            "tweets": 1796
        },
        {
            "username": "@R_AdelJKT48",
            "follower": 28755,
            "following": 117,
            "likes": 415,
            "tweets": 1235
        },
        {
            "username": "@A_AfiqahJKT48",
            "follower": 32757,
            "following": 123,
            "likes": 1183,
            "tweets": 1068
        },
        {
            "username": "@N_AraJKT48",
            "follower": 38166,
            "following": 98,
            "likes": 178,
            "tweets": 1650
        },
        {
            "username": "@C_OnielJKT48",
            "follower": 33524,
            "following": 117,
            "likes": 134,
            "tweets": 1415
        },
        {
            "username": "@A_LuluJKT48",
            "follower": 25289,
            "following": 118,
            "likes": 236,
            "tweets": 1584
        },
        {
            "username": "@G_VanyJKT48",
            "follower": 27217,
            "following": 117,
            "likes": 396,
            "tweets": 1217
        },
        {
            "username": "@A_AlmaJKT48",
            "follower": 37129,
            "following": 91,
            "likes": 178,
            "tweets": 2721
        },
        {
            "username": "@C_JesslynJKT48",
            "follower": 43743,
            "following": 112,
            "likes": 75,
            "tweets": 2999
        },
        {
            "username": "@Freya_JKT48",
            "follower": 46472,
            "following": 139,
            "likes": 2517,
            "tweets": 1714
        },
        {
            "username": "@F_OllaJKT48",
            "follower": 35654,
            "following": 117,
            "likes": 160,
            "tweets": 2573
        },
        {
            "username": "@F_BriJKT48",
            "follower": 28397,
            "following": 96,
            "likes": 388,
            "tweets": 3288
        },
        {
            "username": "@C_JessiJKT48",
            "follower": 40512,
            "following": 138,
            "likes": 7198,
            "tweets": 3399
        },
        {
            "username": "@H_AikoJKT48",
            "follower": 29399,
            "following": 94,
            "likes": 2653,
            "tweets": 2347
        },
        {
            "username": "@Y_ChikaJKT48",
            "follower": 73955,
            "following": 101,
            "likes": 448,
            "tweets": 1877
        },
        {
            "username": "@F_ViviJKT48",
            "follower": 71746,
            "following": 112,
            "likes": 114,
            "tweets": 2280
        },
        {
            "username": "@N_LalaJKT48",
            "follower": 130305,
            "following": 128,
            "likes": 325,
            "tweets": 2681
        },
        {
            "username": "@A_MutheJKT48",
            "follower": 58806,
            "following": 106,
            "likes": 437,
            "tweets": 4582
        },
        {
            "username": "@K_FebiJKT48",
            "follower": 38492,
            "following": 206,
            "likes": 3082,
            "tweets": 3917
        },
        {
            "username": "@A_DeyJKT48",
            "follower": 69206,
            "following": 90,
            "likes": 874,
            "tweets": 1898
        },
        {
            "username": "@A_ZeeJKT48",
            "follower": 106947,
            "following": 97,
            "likes": 554,
            "tweets": 3904
        },
        {
            "username": "@A_YoriJKT48",
            "follower": 60940,
            "following": 120,
            "likes": 6759,
            "tweets": 2900
        },
        {
            "username": "@G_BrielleJKT48",
            "follower": 70395,
            "following": 108,
            "likes": 392,
            "tweets": 2808
        },
        {
            "username": "@H_EliJKT48",
            "follower": 63237,
            "following": 123,
            "likes": 773,
            "tweets": 3000
        },
        {
            "username": "@A_ChristyJKT48",
            "follower": 76085,
            "following": 115,
            "likes": 2333,
            "tweets": 3346
        },
        {
            "username": "@N_TasyaJKT48",
            "follower": 58665,
            "following": 94,
            "likes": 107,
            "tweets": 4449
        },
        {
            "username": "@C_ArielJKT48",
            "follower": 88653,
            "following": 98,
            "likes": 247,
            "tweets": 4018
        },
        {
            "username": "@A_GitaJKT48",
            "follower": 56326,
            "following": 116,
            "likes": 139,
            "tweets": 2439
        },
        {
            "username": "@R_IndyJKT48",
            "follower": 67198,
            "following": 109,
            "likes": 235,
            "tweets": 2746
        },
        {
            "username": "@S_NandaJKT48",
            "follower": 67839,
            "following": 139,
            "likes": 794,
            "tweets": 5362
        },
        {
            "username": "@R_AmelJKT48",
            "follower": 249391,
            "following": 97,
            "likes": 130,
            "tweets": 5086
        },
        {
            "username": "@G_ShalzaJKT48",
            "follower": 39624,
            "following": 110,
            "likes": 136,
            "tweets": 4612
        },
        {
            "username": "@Julie_JKT48",
            "follower": 82557,
            "following": 119,
            "likes": 885,
            "tweets": 6132
        },
        {
            "username": "@AyaJKT48_",
            "follower": 89282,
            "following": 133,
            "likes": 500,
            "tweets": 5422
        },
        {
            "username": "@Gabryela_JKT48",
            "follower": 81453,
            "following": 112,
            "likes": 18,
            "tweets": 6749
        },
        {
            "username": "@Eve_JKT48",
            "follower": 170421,
            "following": 96,
            "likes": 2157,
            "tweets": 4880
        },
        {
            "username": "@Diani_JKT48",
            "follower": 71207,
            "following": 125,
            "likes": 373,
            "tweets": 6892
        },
        {
            "username": "@Jinan_JKT48",
            "follower": 100394,
            "following": 141,
            "likes": 2183,
            "tweets": 5815
        },
        {
            "username": "@Celine_JKT48",
            "follower": 93696,
            "following": 136,
            "likes": 271,
            "tweets": 5443
        },
        {
            "username": "@Melati_JKT48",
            "follower": 100934,
            "following": 153,
            "likes": 770,
            "tweets": 7647
        },
        {
            "username": "@Fidly_JKT48",
            "follower": 109391,
            "following": 162,
            "likes": 485,
            "tweets": 12966
        },
        {
            "username": "@CindyH_JKT48",
            "follower": 149995,
            "following": 150,
            "likes": 742,
            "tweets": 8216
        },
        {
            "username": "@Elisabeth_JKT48",
            "follower": 71734,
            "following": 171,
            "likes": 440,
            "tweets": 4137
        },
        {
            "username": "@F_FeniJKT48",
            "follower": 187756,
            "following": 156,
            "likes": 51,
            "tweets": 14484
        },
        {
            "username": "@S_SiscaJKT48",
            "follower": 283769,
            "following": 295,
            "likes": 1084,
            "tweets": 17436
        },
        {
            "username": "@M_DesyJKT48",
            "follower": 302454,
            "following": 352,
            "likes": 2409,
            "tweets": 19009
        },
        {
            "username": "@N_AurelJKT48",
            "follower": 157008,
            "following": 130,
            "likes": 667,
            "tweets": 11608
        },
        {
            "username": "@S_GraciaJKT48",
            "follower": 240262,
            "following": 202,
            "likes": 1141,
            "tweets": 14307
        },
        {
            "username": "@N_ShaniJKT48",
            "follower": 381913,
            "following": 192,
            "likes": 1263,
            "tweets": 12151
        },
        {
            "username": "@R_AninJKT48",
            "follower": 322592,
            "following": 208,
            "likes": 1290,
            "tweets": 16364
        },
        {
            "username": "@bebyJKT48",
            "follower": 570394,
            "following": 204,
            "likes": 173,
            "tweets": 21805
        },
        {
            "username": "@frieskaJKT48",
            "follower": 468617,
            "following": 391,
            "likes": 778,
            "tweets": 12828
        },
        {
            "username": "@gabyJKT48",
            "follower": 413073,
            "following": 245,
            "likes": 596,
            "tweets": 13843
        },
        {
            "username": "@Nadila_JKT48",
            "follower": 424125,
            "following": 176,
            "likes": 1882,
            "tweets": 15071
        },
        {
            "username": "@Ayen_JKT48",
            "follower": 647343,
            "following": 232,
            "likes": 2936,
            "tweets": 10696
        }
    ]
}