{
    "last_update": "2020-10-18T00:00:02",
    "members": [
        {
            "username": "@GNabilaJKT48",
            "follower": 11253,
            "following": 129,
            "likes": 278,
            "tweets": 521
        },
        {
            "username": "@P_ZahraJKT48",
            "follower": 13735,
            "following": 103,
            "likes": 3530,
            "tweets": 844
        },
        {
            "username": "@D_ShintaJKT48",
            "follower": 17480,
            "following": 96,
            "likes": 560,
            "tweets": 724
        },
        {
            "username": "@L_MarshaJKT48",
            "follower": 21908,
            "following": 170,
            "likes": 1602,
            "tweets": 554
        },
        {
            "username": "@I_KathrinaJKT48",
            "follower": 15078,
            "following": 146,
            "likes": 249,
            "tweets": 408
        },
        {
            "username": "@C_IndahJKT48",
            "follower": 16713,
            "following": 90,
            "likes": 15,
            "tweets": 495
        },
        {
            "username": "@E_ChalistaJKT48",
            "follower": 19369,
            "following": 93,
            "likes": 1367,
            "tweets": 616
        },
        {
            "username": "@G_CaithlynJKT48",
            "follower": 15021,
            "following": 119,
            "likes": 1579,
            "tweets": 1019
        },
        {
            "username": "@S_AshelJKT48",
            "follower": 28143,
            "following": 107,
            "likes": 709,
            "tweets": 578
        },
        {
            "username": "@J_AbelJKT48",
            "follower": 12883,
            "following": 122,
            "likes": 775,
            "tweets": 326
        },
        {
            "username": "@N_RatuJKT48",
            "follower": 45157,
            "following": 121,
            "likes": 521,
            "tweets": 992
        },
        {
            "username": "@C_NunuJKT48",
            "follower": 40756,
            "following": 501,
            "likes": 1460,
            "tweets": 1371
        },
        {
            "username": "@M_UmeJKT48",
            "follower": 26313,
            "following": 90,
            "likes": 198,
            "tweets": 1150
        },
        {
            "username": "@S_FloraJKT48",
            "follower": 34207,
            "following": 103,
            "likes": 229,
            "tweets": 678
        },
        {
            "username": "@R_KeisyaJKT48",
            "follower": 34843,
            "following": 94,
            "likes": 444,
            "tweets": 903
        },
        {
            "username": "@F_MiraJKT48",
            "follower": 63628,
            "following": 106,
            "likes": 294,
            "tweets": 2115
        },
        {
            "username": "@A_FionyJKT48",
            "follower": 66197,
            "following": 196,
            "likes": 886,
            "tweets": 2391
        },
        {
            "username": "@R_AdelJKT48",
            "follower": 43102,
            "following": 116,
            "likes": 554,
            "tweets": 1626
        },
        {
            "username": "@A_AfiqahJKT48",
            "follower": 42333,
            "following": 125,
            "likes": 1473,
            "tweets": 1538
        },
        {
            "username": "@N_AraJKT48",
            "follower": 56530,
            "following": 101,
            "likes": 221,
            "tweets": 2167
        },
        {
            "username": "@C_OnielJKT48",
            "follower": 48872,
            "following": 114,
            "likes": 184,
            "tweets": 2050
        },
        {
            "username": "@A_LuluJKT48",
            "follower": 39919,
            "following": 118,
            "likes": 234,
            "tweets": 2380
        },
        {
            "username": "@G_VanyJKT48",
            "follower": 41186,
            "following": 149,
            "likes": 607,
            "tweets": 1682
        },
        {
            "username": "@C_JesslynJKT48",
            "follower": 62270,
            "following": 113,
            "likes": 85,
            "tweets": 3512
        },
        {
            "username": "@Freya_JKT48",
            "follower": 63265,
            "following": 140,
            "likes": 3541,
            "tweets": 2244
        },
        {
            "username": "@F_OllaJKT48",
            "follower": 53268,
            "following": 115,
            "likes": 263,
            "tweets": 3386
        },
        {
            "username": "@F_BriJKT48",
            "follower": 39809,
            "following": 96,
            "likes": 501,
            "tweets": 4106
        },
        {
            "username": "@C_JessiJKT48",
            "follower": 56205,
            "following": 130,
            "likes": 7705,
            "tweets": 3939
        },
        {
            "username": "@Y_ChikaJKT48",
            "follower": 103063,
            "following": 99,
            "likes": 474,
            "tweets": 2299
        },
        {
            "username": "@F_ViviJKT48",
            "follower": 94814,
            "following": 109,
            "likes": 128,
            "tweets": 2284
        },
        {
            "username": "@N_LalaJKT48",
            "follower": 177654,
            "following": 126,
            "likes": 339,
            "tweets": 2977
        },
        {
            "username": "@A_MutheJKT48",
            "follower": 78957,
            "following": 104,
            "likes": 471,
            "tweets": 5024
        },
        {
            "username": "@K_FebiJKT48",
            "follower": 47106,
            "following": 210,
            "likes": 3145,
            "tweets": 4261
        },
        {
            "username": "@A_DeyJKT48",
            "follower": 89064,
            "following": 92,
            "likes": 924,
            "tweets": 2303
        },
        {
            "username": "@A_ZeeJKT48",
            "follower": 145195,
            "following": 98,
            "likes": 717,
            "tweets": 4601
        },
        {
            "username": "@A_YoriJKT48",
            "follower": 83947,
            "following": 118,
            "likes": 7771,
            "tweets": 4466
        },
        {
            "username": "@G_BrielleJKT48",
            "follower": 95980,
            "following": 111,
            "likes": 395,
            "tweets": 3278
        },
        {
            "username": "@H_EliJKT48",
            "follower": 81241,
            "following": 137,
            "likes": 1060,
            "tweets": 3704
        },
        {
            "username": "@A_ChristyJKT48",
            "follower": 104267,
            "following": 115,
            "likes": 2685,
            "tweets": 3887
        },
        {
            "username": "@N_TasyaJKT48",
            "follower": 90321,
            "following": 96,
            "likes": 126,
            "tweets": 5127
        },
        {
            "username": "@C_ArielJKT48",
            "follower": 118513,
            "following": 97,
            "likes": 248,
            "tweets": 4632
        },
        {
            "username": "@A_GitaJKT48",
            "follower": 72078,
            "following": 116,
            "likes": 135,
            "tweets": 2786
        },
        {
            "username": "@R_IndyJKT48",
            "follower": 91353,
            "following": 105,
            "likes": 232,
            "tweets": 3005
        },
        {
            "username": "@S_NandaJKT48",
            "follower": 90480,
            "following": 135,
            "likes": 809,
            "tweets": 5661
        },
        {
            "username": "@R_AmelJKT48",
            "follower": 327072,
            "following": 94,
            "likes": 127,
            "tweets": 5509
        },
        {
            "username": "@Julie_JKT48",
            "follower": 105914,
            "following": 120,
            "likes": 985,
            "tweets": 6695
        },
        {
            "username": "@AyaJKT48_",
            "follower": 98790,
            "following": 132,
            "likes": 25,
            "tweets": 5932
        },
        {
            "username": "@Gabryela_JKT48",
            "follower": 102294,
            "following": 108,
            "likes": 18,
            "tweets": 7061
        },
        {
            "username": "@Eve_JKT48",
            "follower": 215805,
            "following": 95,
            "likes": 2164,
            "tweets": 5422
        },
        {
            "username": "@Diani_JKT48",
            "follower": 87168,
            "following": 123,
            "likes": 384,
            "tweets": 7288
        },
        {
            "username": "@Jinan_JKT48",
            "follower": 113149,
            "following": 140,
            "likes": 2255,
            "tweets": 6097
        },
        {
            "username": "@Celine_JKT48",
            "follower": 109956,
            "following": 139,
            "likes": 329,
            "tweets": 6018
        },
        {
            "username": "@Melati_JKT48",
            "follower": 114566,
            "following": 149,
            "likes": 810,
            "tweets": 7959
        },
        {
            "username": "@Fidly_JKT48",
            "follower": 121579,
            "following": 168,
            "likes": 514,
            "tweets": 13587
        },
        {
            "username": "@CindyH_JKT48",
            "follower": 172522,
            "following": 150,
            "likes": 764,
            "tweets": 8810
        },
        {
            "username": "@Elisabeth_JKT48",
            "follower": 80062,
            "following": 166,
            "likes": 451,
            "tweets": 4308
        },
        {
            "username": "@F_FeniJKT48",
            "follower": 200483,
            "following": 152,
            "likes": 55,
            "tweets": 14894
        },
        {
            "username": "@S_SiscaJKT48",
            "follower": 303888,
            "following": 343,
            "likes": 1171,
            "tweets": 18108
        },
        {
            "username": "@M_DesyJKT48",
            "follower": 320771,
            "following": 357,
            "likes": 2719,
            "tweets": 19671
        },
        {
            "username": "@N_AurelJKT48",
            "follower": 167698,
            "following": 128,
            "likes": 668,
            "tweets": 11857
        },
        {
            "username": "@S_GraciaJKT48",
            "follower": 255216,
            "following": 212,
            "likes": 1355,
            "tweets": 15096
        },
        {
            "username": "@N_ShaniJKT48",
            "follower": 411184,
            "following": 207,
            "likes": 1406,
            "tweets": 12821
        },
        {
            "username": "@R_AninJKT48",
            "follower": 353781,
            "following": 204,
            "likes": 1408,
            "tweets": 16735
        },
        {
            "username": "@bebyJKT48",
            "follower": 579174,
            "following": 202,
            "likes": 185,
            "tweets": 22604
        },
        {
            "username": "@frieskaJKT48",
            "follower": 477807,
            "following": 402,
            "likes": 1179,
            "tweets": 13923
        },
        {
            "username": "@gabyJKT48",
            "follower": 421449,
            "following": 240,
            "likes": 610,
            "tweets": 14442
        },
        {
            "username": "@Nadila_JKT48",
            "follower": 433578,
            "following": 175,
            "likes": 1885,
            "tweets": 15630
        },
        {
            "username": "@Ayen_JKT48",
            "follower": 655883,
            "following": 230,
            "likes": 2980,
            "tweets": 10996
        }
    ]
}